mvmtAD/AD.py
mvmtAD/Roots.py
mvmtAD/__init__.py
mvmtAD/bfgs.py
mvmtAD/tests/__init__.py
mvmtAD/tests/test_bfgs.py
mvmtAD/tests/test_integration.py
mvmtAD/tests/test_roots.py
mvmtAD/tests/test_unit.py
mvmtAD-1.1.dist-info/LICENSE
mvmtAD-1.1.dist-info/METADATA
mvmtAD-1.1.dist-info/WHEEL
mvmtAD-1.1.dist-info/top_level.txt
mvmtAD-1.1.dist-info/RECORD
