Metadata-Version: 2.1
Name: mvmtAD
Version: 1.1
Summary: Forward mode automatic differentiation package.
Home-page: https://github.com/MVMT107/cs107-FinalProject
Author: Victoria DiTomasso, Martha Obasi, Matt Egan, Thomas Shay Hill
Author-email: UNKNOWN
License: UNKNOWN
Platform: UNKNOWN
Requires-Dist: numpy
Requires-Dist: scipy
